CHANGES.txt
MANIFEST.in
README.txt
__main__.py
bootstrap.py
buildout.cfg
jslex.py
jslex_scripts.py
setup.py
tests.py
unirange.py
jslex.egg-info/PKG-INFO
jslex.egg-info/SOURCES.txt
jslex.egg-info/dependency_links.txt
jslex.egg-info/entry_points.txt
jslex.egg-info/not-zip-safe
jslex.egg-info/top_level.txt