Metadata-Version: 1.0
Name: jslex
Version: 0.2.1
Summary: JsLex makes JavaScript more edible by xgettext (in C mode).
Home-page: https://bitbucket.org/ned/jslex
Author: Ned Batchelder
Author-email: UNKNOWN
License: BSD
Platform: UNKNOWN
